qd_machine_hk/MachineLogAnalytics.py
qd_machine_hk/ParentMachineInterface.cp311-win_amd64.pyd
qd_machine_hk/SystemInfo.py
qd_machine_hk/__init__.py
qd_machine_hk-0.4.dist-info/LICENSE.txt
qd_machine_hk-0.4.dist-info/METADATA
qd_machine_hk-0.4.dist-info/WHEEL
qd_machine_hk-0.4.dist-info/top_level.txt
qd_machine_hk-0.4.dist-info/RECORD
